[
  {"id":"bay-mare","name":"Bay Mare","slot":"transportation","rarity":"common","file":"assets/transportation/01-bay-mare.png","description":"A sure-footed bay mare with a simple riding saddle, dependable for travel between settlements and inland trails."},
  {"id":"gray-gelding","name":"Gray Gelding","slot":"transportation","rarity":"common","file":"assets/transportation/02-gray-gelding.png","description":"A calm gray gelding valued for steady work, road travel, and the long distances of the Atlantic frontier."},
  {"id":"chestnut-stallion","name":"Chestnut Stallion","slot":"transportation","rarity":"uncommon","file":"assets/transportation/03-chestnut-stallion.png","description":"A spirited chestnut horse with the strength and speed to carry a rider across rough colonial roads."},
  {"id":"dappled-trail-horse","name":"Dappled Trail Horse","slot":"transportation","rarity":"uncommon","file":"assets/transportation/04-dappled-trail-horse.png","description":"A dappled riding horse suited to explorers, messengers, and travelers moving beyond established settlements."},
  {"id":"pack-horse","name":"Pack Horse","slot":"transportation","rarity":"uncommon","file":"assets/transportation/05-pack-horse.png","description":"A saddle-equipped pack horse prepared to carry supplies, maps, and trade goods overland."},
  {"id":"surveyors-mule","name":"Surveyor's Mule","slot":"transportation","rarity":"common","file":"assets/transportation/06-surveyors-mule.png","description":"A hardy mule prized for balance and endurance when carrying instruments across uneven ground."},
  {"id":"coastal-pony","name":"Coastal Pony","slot":"transportation","rarity":"common","file":"assets/transportation/07-coastal-pony.png","description":"A compact pony well suited to coastal paths, smaller settlements, and everyday travel along the Atlantic shore."},
  {"id":"merchants-wagon","name":"Merchant's Wagon","slot":"transportation","rarity":"rare","file":"assets/transportation/08-merchants-wagon.png","description":"A covered wagon for moving cargo, household goods, and trade supplies between ports, markets, and inland communities."},
  {"id":"fishing-dory","name":"Fishing Dory","slot":"transportation","rarity":"uncommon","file":"assets/transportation/09-fishing-dory.png","description":"A sturdy small wooden boat for coastal fishing, short harbor crossings, and work along Atlantic waterways."},
  {"id":"atlantic-sloop","name":"Atlantic Sloop","slot":"transportation","rarity":"rare","file":"assets/transportation/10-atlantic-sloop.png","description":"A small sailing vessel prepared for coastal trade and exploration, carrying travelers between ports of the Atlantic world."}
]
